indeed_mongodb_scrapper/__init__.py
indeed_mongodb_scrapper/__main__.py
indeed_mongodb_scrapper/scraping.py
indeed_mongodb_scrapper/__pycache__/__init__.cpython-38.pyc
indeed_mongodb_scrapper/__pycache__/scraping.cpython-38.pyc
tests/__init__.py
tests/test.py
indeed_mongodb_scrapper-0.1.1.dist-info/METADATA
indeed_mongodb_scrapper-0.1.1.dist-info/WHEEL
indeed_mongodb_scrapper-0.1.1.dist-info/entry_points.txt
indeed_mongodb_scrapper-0.1.1.dist-info/top_level.txt
indeed_mongodb_scrapper-0.1.1.dist-info/RECORD
