Metadata-Version: 2.1
Name: indeed-mongodb-scrapper
Version: 0.1.1
Summary: "Indeed Scrapper storing the data on MongoDB database"
Home-page: https://github.com/YacineAll/indeed_mongodb_scrapper
Author: Yacine ALLOUACHE
Author-email: yacine.allouache1996@gmail.com
License: MIT
Project-URL: Source, https://github.com/YacineAll/indeed_mongodb_scrapper
Keywords: scrapping,indeed,jobs,mongodb
Platform: any
Classifier: Development Status :: 4 - Beta
Classifier: Intended Audience :: Science/Research
Classifier: Programming Language :: Python
Classifier: Programming Language :: Python :: 3.8
Classifier: Topic :: Software Development :: Libraries :: Python Modules
Requires-Python: >=3.8
Requires-Dist: pymongo (==3.11.3)
Requires-Dist: tqdm (==4.59.0)
Requires-Dist: requests (==2.25.1)
Requires-Dist: beautifulsoup4 (==4.9.3)
Provides-Extra: test
Requires-Dist: pytest (==6.2.3) ; extra == 'test'
